textfromimage/__init__.py
textfromimage/azure_openai.py
textfromimage/claude.py
textfromimage/openai.py
textfromimage/utils.py
textfromimage-1.1.1.dist-info/LICENSE
textfromimage-1.1.1.dist-info/METADATA
textfromimage-1.1.1.dist-info/WHEEL
textfromimage-1.1.1.dist-info/top_level.txt
textfromimage-1.1.1.dist-info/RECORD
