Metadata-Version: 2.1
Name: textfromimage
Version: 1.1.1
Summary: Get descriptions of images from OpenAI, Azure OpenAI, and Anthropic Claude models with support for local files and batch processing.
Home-page: https://github.com/OrenGrinker/textfromimage
Author: Oren Grinker
Author-email: orengr4@gmail.com
Project-URL: Bug Reports, https://github.com/OrenGrinker/textfromimage/issues
Project-URL: Source, https://github.com/OrenGrinker/textfromimage
Keywords: openai,gpt-4,claude,azure-openai,computer-vision,image-to-text,ai,machine-learning,batch-processing,local-files,image-analysis,vision-ai
Classifier: Programming Language :: Python :: 3
Classifier: License :: OSI Approved :: MIT License
Classifier: Operating System :: OS Independent
Classifier: Development Status :: 4 - Beta
Classifier: Intended Audience :: Developers
Classifier: Topic :: Scientific/Engineering :: Artificial Intelligence
Classifier: Topic :: Software Development :: Libraries :: Python Modules
Classifier: Programming Language :: Python :: 3.9
Classifier: Programming Language :: Python :: 3.10
Classifier: Programming Language :: Python :: 3.11
Requires-Python: >=3.9
License-File: LICENSE
Requires-Dist: openai>=1.35.15
Requires-Dist: requests>=2.25.1
Requires-Dist: anthropic>=0.18.1
Requires-Dist: typing-extensions>=4.5.0
Provides-Extra: azure
Requires-Dist: azure-identity>=1.15.0; extra == "azure"
Provides-Extra: all
Requires-Dist: azure-identity>=1.15.0; extra == "all"
Requires-Dist: aiohttp>=3.8.0; extra == "all"
Requires-Dist: python-magic>=0.4.27; extra == "all"
